HAT/HAT.py
HAT/__init__.py
HAT/datasets.py
HAT/draw.py
HAT/dynamics.py
HAT/export.py
HAT/graph.py
HAT/hypergraph.py
HAT/laplacian.py
HAT/metrics.py
HAT/multilinalg.py
HAT/tensors.py
HAT/data/aminer_cocitation.mat
HAT/data/aminer_coreference.mat
HAT/data/citeseer_cocitation.mat
HAT/data/citeseer_coreference.mat
HAT/data/cora_cocitation.mat
HAT/data/cora_coreference.mat
HAT/data/dblp.mat
hypergraphanalysistoolbox-1.1.16.dist-info/METADATA
hypergraphanalysistoolbox-1.1.16.dist-info/WHEEL
hypergraphanalysistoolbox-1.1.16.dist-info/licenses/LICENSE
hypergraphanalysistoolbox-1.1.16.dist-info/RECORD
