Metadata-Version: 2.4
Name: HypergraphAnalysisToolbox
Version: 1.1.16
Summary: This package performes hypergraph analysis.
Project-URL: Homepage, https://hypergraph-analysis-toolbox.readthedocs.io/en/latest/
Project-URL: Bug Tracker, https://github.com/Jpickard1/Hypergraph-Analysis-Toolbox/issues
Author-email: Joshua Pickard <jpic@umich.edu>
License-File: LICENSE
Classifier: License :: OSI Approved :: MIT License
Classifier: Operating System :: OS Independent
Classifier: Programming Language :: Python :: 3
Requires-Python: >=3.11
Requires-Dist: matplotlib
Requires-Dist: networkx
Requires-Dist: numpy
Requires-Dist: pandas
Requires-Dist: rich
Requires-Dist: scipy
Requires-Dist: tqdm
Provides-Extra: docs
Requires-Dist: mock; extra == 'docs'
